vdraw/__init__.py
vdraw/semantic_segmentation/__init__.py
vdraw/semantic_segmentation/bbox.py
vdraw/semantic_segmentation/utils/__init__.py
vdraw/semantic_segmentation/utils/clean.py
vdraw/semantic_segmentation/utils/draw.py
vdraw/semantic_segmentation/utils/find.py
vdraw-0.1.4.dist-info/METADATA
vdraw-0.1.4.dist-info/WHEEL
vdraw-0.1.4.dist-info/top_level.txt
vdraw-0.1.4.dist-info/RECORD
